todoman/__init__.py
todoman/__main__.py
todoman/cli.py
todoman/configuration.py
todoman/exceptions.py
todoman/formatters.py
todoman/interactive.py
todoman/model.py
todoman/version.py
todoman/widgets.py
todoman-4.6.0.dist-info/licenses/LICENCE
todoman-4.6.0.dist-info/METADATA
todoman-4.6.0.dist-info/WHEEL
todoman-4.6.0.dist-info/entry_points.txt
todoman-4.6.0.dist-info/top_level.txt
todoman-4.6.0.dist-info/RECORD
