Metadata-Version: 2.4
Name: todoman
Version: 4.6.0
Summary: A simple icalendar-based todo manager.
Author-email: Hugo Osvaldo Barrera <hugo@whynothugo.nl>
License-Expression: ISC
Project-URL: homepage, https://github.com/pimutils/todoman
Project-URL: documentation, https://todoman.readthedocs.io/
Project-URL: changelog, https://github.com/pimutils/todoman/blob/main/CHANGELOG.rst
Project-URL: issues, https://github.com/pimutils/todoman/issues
Keywords: todo,task,icalendar,cli
Classifier: Development Status :: 5 - Production/Stable
Classifier: Environment :: Console
Classifier: Environment :: Console :: Curses
Classifier: Operating System :: POSIX
Classifier: Programming Language :: Python :: 3
Classifier: Programming Language :: Python :: 3.9
Classifier: Programming Language :: Python :: 3.10
Classifier: Programming Language :: Python :: 3.11
Classifier: Programming Language :: Python :: 3.12
Classifier: Programming Language :: Python :: Implementation :: PyPy
Classifier: Topic :: Office/Business :: Scheduling
Classifier: Topic :: Utilities
Requires-Python: >=3.9
License-File: LICENCE
Requires-Dist: click<9.0,>=7.1
Requires-Dist: click-log>=0.2.1
Requires-Dist: humanize
Requires-Dist: icalendar>=4.0.3
Requires-Dist: parsedatetime
Requires-Dist: python-dateutil
Requires-Dist: pyxdg
Requires-Dist: urwid
Provides-Extra: lint
Requires-Dist: ruff; extra == "lint"
Requires-Dist: mypy; extra == "lint"
Requires-Dist: types-pytz; extra == "lint"
Requires-Dist: types-python-dateutil; extra == "lint"
Provides-Extra: test
Requires-Dist: freezegun; extra == "test"
Requires-Dist: hypothesis; extra == "test"
Requires-Dist: pytest; extra == "test"
Requires-Dist: pytest-cov; extra == "test"
Requires-Dist: pytz; extra == "test"
Provides-Extra: docs
Requires-Dist: sphinx-click; extra == "docs"
Requires-Dist: sphinx_rtd_theme; extra == "docs"
Provides-Extra: repl
Requires-Dist: click-repl>=0.1.6; extra == "repl"
Dynamic: license-file
